[
  {
    "id": "c1665f65-d675-486d-9950-a9d8416dda9c",
    "fullName": "dafdfad",
    "phone": "3323",
    "transactions": [
      {
        "orders": [
          {
            "productName": "L298 Motor Driver Module",
            "quantity": 1
          },
          {
            "productName": "UNO CNC Shield V3 Engraving Machine",
            "quantity": 1
          }
        ],
        "amount": 0,
        "courses": [
          {
            "productName": "JavaScript Monster",
            "quantity": 1
          }
        ]
      }
    ]
  }
]